{
  "active_plan": "/Users/hassoncs/Workspaces/Personal/slopcade/.sisyphus/plans/godot-ui-theming-system-v2.md",
  "started_at": "2026-01-26T03:51:58.747Z",
  "completed_at": "2026-01-26T04:10:32.000Z",
  "session_ids": [
    "ses_407ee5706ffeNnik9xSrYLjLa2",
    "ses_40774f7f5ffe8wBR1mtYpiCp90"
  ],
  "plan_name": "godot-ui-theming-system-v2",
  "status": "partially_complete",
  "progress": "9/13 tasks (69%)",
  "notes": "Backend pipeline fully functional (Phases 1-3 + Task 12). Remaining: Godot integration (Tasks 9-11) and manual QA (Task 13) require user action. See .sisyphus/completed/2026-01/godot-ui-theming-implementation.md for full details."
}